<?xml version="1.0" encoding="UTF-8" standalone="yes"?><flusso_ordinativi><testata_flusso><codice_ABI_BT>01005</codice_ABI_BT><identificativo_flusso>OPIUF1KEY20200000231</identificativo_flusso><data_ora_creazione_flusso>2020-02-12T13:33:29</data_ora_creazione_flusso><codice_ente>UF1KEY</codice_ente><descrizione_ente>AZIENDA SANITARIA PROVINCIALE DI REGGIO CALABRIA</descrizione_ente><codice_istat_ente>026279471000000</codice_istat_ente><codice_fiscale_ente>02638720801</codice_fiscale_ente><codice_tramite_ente>A2A-51955550</codice_tramite_ente><codice_tramite_BT>A2A-70941793</codice_tramite_BT><codice_ente_BT>0004172</codice_ente_BT></testata_flusso><esercizio>2020</esercizio><mandato><tipo_operazione>INSERIMENTO</tipo_operazione><numero_mandato>1765</numero_mandato><data_mandato>2020-02-12</data_mandato><importo_mandato>7870.23</importo_mandato><informazioni_beneficiario><progressivo_beneficiario>1</progressivo_beneficiario><importo_beneficiario>7870.23</importo_beneficiario><tipo_pagamento>SEPA CREDIT TRANSFER</tipo_pagamento><destinazione>LIBERA</destinazione><tipo_contabilita_ente_ricevente>FRUTTIFERA</tipo_contabilita_ente_ricevente><classificazione><codice_cgu>3214</codice_cgu><importo>7870.23</importo><classificazione_dati_siope_uscite><tipo_debito_siope_c>COMMERCIALE</tipo_debito_siope_c><codice_cig_siope>Z2F2ACB434</codice_cig_siope><fattura_siope><codice_ipa_ente_siope>UF1KEY</codice_ipa_ente_siope><tipo_documento_siope_e>ELETTRONICO</tipo_documento_siope_e><identificativo_lotto_sdi_siope>2250427694</identificativo_lotto_sdi_siope><dati_fattura_siope><numero_fattura_siope>FPA 4/19</numero_fattura_siope><importo_siope>9601.68</importo_siope><data_scadenza_pagam_siope>2020-03-31</data_scadenza_pagam_siope><natura_spesa_siope>CORRENTE</natura_spesa_siope></dati_fattura_siope></fattura_siope></classificazione_dati_siope_uscite></classificazione><bollo><assoggettamento_bollo>ESENTE BOLLO</assoggettamento_bollo><causale_esenzione_bollo>ESENTE BOLLO IN QUANTO DOCUMENTI ASSOGGETTATI AD IVA</causale_esenzione_bollo></bollo><spese><soggetto_destinatario_delle_spese>ESENTE</soggetto_destinatario_delle_spese><causale_esenzione_spese>NESSUNA SPESA</causale_esenzione_spese></spese><beneficiario><anagrafica_beneficiario>ENERGIALIMPIA SRL</anagrafica_beneficiario><indirizzo_beneficiario>VIA CONTRADA CONTURA N 2</indirizzo_beneficiario><cap_beneficiario>89024</cap_beneficiario><localita_beneficiario>POLISTENA</localita_beneficiario><provincia_beneficiario>RC</provincia_beneficiario><stato_beneficiario>IT</stato_beneficiario><partita_iva_beneficiario>02633020801</partita_iva_beneficiario></beneficiario><sepa_credit_transfer><iban>IT16D0760116300001037334479</iban></sepa_credit_transfer><causale>CIG: Z2F2ACB434 Fatture: FPA4/19/19</causale><informazioni_aggiuntive><lingua>ITALIANO</lingua></informazioni_aggiuntive></informazioni_beneficiario></mandato></flusso_ordinativi>